README.md
setup.cfg
setup.py
proxy_parser/__init__.py
proxy_parser/proxy_parser.py
proxy_parser.egg-info/PKG-INFO
proxy_parser.egg-info/SOURCES.txt
proxy_parser.egg-info/dependency_links.txt
proxy_parser.egg-info/not-zip-safe
proxy_parser.egg-info/top_level.txt