Metadata-Version: 1.0
Name: proxy-parser
Version: 0.2
Summary: by @bu77h4ad
Home-page: UNKNOWN
Author: UNKNOWN
Author-email: razor-men@mail.ru
License: UNKNOWN
Platform: UNKNOWN
